improvisers/__init__.py
improvisers/critic.py
improvisers/explicit.py
improvisers/game_graph.py
improvisers/implicit.py
improvisers/policy.py
improvisers/py.typed
improvisers/tabular.py
improvisers-0.1.7.dist-info/LICENSE
improvisers-0.1.7.dist-info/WHEEL
improvisers-0.1.7.dist-info/METADATA
improvisers-0.1.7.dist-info/RECORD
