Metadata-Version: 2.1
Name: improvisers
Version: 0.1.7
Summary: Library for modeling improvisers in stochastic games.
Author: Marcell Vazquez-Chanlatte
Author-email: mvc@linux.com
Requires-Python: >=3.8,<4.0
Classifier: Programming Language :: Python :: 3
Classifier: Programming Language :: Python :: 3.8
Classifier: Programming Language :: Python :: 3.9
Requires-Dist: attrs (>=20.3.0,<21.0.0)
Requires-Dist: scipy (>=1.5.4,<2.0.0)
Requires-Dist: toposort (>=1.5,<2.0)
